MANIFEST.in
README.rst
setup.py
collective/.DS_Store
collective/__init__.py
collective/__init__.pyc
collective.ptg.carousel.egg-info/PKG-INFO
collective.ptg.carousel.egg-info/SOURCES.txt
collective.ptg.carousel.egg-info/dependency_links.txt
collective.ptg.carousel.egg-info/entry_points.txt
collective.ptg.carousel.egg-info/namespace_packages.txt
collective.ptg.carousel.egg-info/not-zip-safe
collective.ptg.carousel.egg-info/requires.txt
collective.ptg.carousel.egg-info/top_level.txt
collective/ptg/.DS_Store
collective/ptg/__init__.py
collective/ptg/__init__.pyc
collective/ptg/carousel/__init__.py
collective/ptg/carousel/__init__.pyc
collective/ptg/carousel/carousel.pt
collective/ptg/carousel/configure.zcml
collective/ptg/carousel/i18n.sh
collective/ptg/carousel/locales/.DS_Store
collective/ptg/carousel/locales/en/.DS_Store
collective/ptg/carousel/locales/en/LC_MESSAGES/.DS_Store
collective/ptg/carousel/locales/no/.DS_Store
collective/ptg/carousel/locales/no/LC_MESSAGES/.DS_Store
collective/ptg/carousel/resources/credits.txt
collective/ptg/carousel/resources/jquery.jcarousel.js
collective/ptg/carousel/resources/jquery.jcarousel.min.js
collective/ptg/carousel/resources/next-horizontal.png
collective/ptg/carousel/resources/next-vertical.png
collective/ptg/carousel/resources/no_style.css
collective/ptg/carousel/resources/prev-horizontal.png
collective/ptg/carousel/resources/prev-vertical.png
collective/ptg/carousel/resources/style.css
docs/HISTORY.txt
docs/INSTALL.txt
docs/LICENSE.GPL
docs/LICENSE.txt