Metadata-Version: 1.0
Name: collective.ptg.carousel
Version: 0.1
Summary: carousel gallery type for plonetruegallery
Home-page: https://github.com/collective/collective.ptg.carousel
Author: Espen Moe-Nilssen
Author-email: espen@medialog.no
License: GPL
Keywords: plonetruegallery gallery plone addon carousel
Platform: UNKNOWN
Classifier: Framework :: Plone
Classifier: Programming Language :: Python
